frenamer/__init__.py
frenamer/__main__.py
frenamer/frenamer.py
frenamer/version.py
frenamer-0.2.3.dist-info/LICENSE
frenamer-0.2.3.dist-info/METADATA
frenamer-0.2.3.dist-info/WHEEL
frenamer-0.2.3.dist-info/entry_points.txt
frenamer-0.2.3.dist-info/top_level.txt
frenamer-0.2.3.dist-info/RECORD
