Metadata-Version: 2.1
Name: frenamer
Version: 0.2.3
Summary: Rename and unrename all files in the directory, alphabetically or randomly
Home-page: https://github.com/TheAwiteb/frenamer
Author: TheAwiteb
Author-email: Awiteb@hotmail.com
License: MIT
Keywords: frenamer,renamer,file_renamer,file,file renamer
Platform: UNKNOWN
Classifier: Programming Language :: Python :: 3.8
Classifier: Programming Language :: Python :: 3.9
Classifier: Programming Language :: Python :: 3.10
Classifier: License :: OSI Approved :: MIT License
Classifier: Operating System :: OS Independent
Requires-Python: >=3.8
License-File: LICENSE
Requires-Dist: certifi (==2021.10.8)
Requires-Dist: charset-normalizer (==2.0.8)
Requires-Dist: click (==8.0.3)
Requires-Dist: idna (==3.3)
Requires-Dist: requests (==2.26.0)
Requires-Dist: typer (==0.4.0)
Requires-Dist: urllib3 (==1.26.7)
